Metadata-Version: 1.1
Name: icsv
Version: 0.1.6
Summary: A simple script to make operating csv files easier
Home-page: https://www.samuelworks.org
Author: Samuel Mtembo
Author-email: samuel@samuelworks.org
License: MIT
Download-URL: https://github.com/qodzero/icsv/archive/v1.0.6.tar.gz
Keywords: csv
Platform: UNKNOWN
Classifier: Development Status :: 3 - Alpha
Classifier: Intended Audience :: Developers
Classifier: Topic :: Software Development :: Build Tools
Classifier: License :: OSI Approved :: MIT License
Classifier: Programming Language :: Python :: 3
Classifier: Programming Language :: Python :: 3.4
Classifier: Programming Language :: Python :: 3.5
Classifier: Programming Language :: Python :: 3.6
